Workbook

Sheet _Data
A1: order_id | B1: order_date_std | C1: ship_date_std | D1: customer_id | E1: customer_name | F1: segment | G1: region | H1: state | I1: city | J1: category | K1: sub_category | L1: product_name | M1: ship_mode | N1: quantity | O1: unit_price | P1: cleaned_discount | Q1: sales | R1: cost | S1: payment_status | T1: order_status | U1: calc_sales | V1: calc_profit | W1: order_month | X1: order_year
A2: ORD-2024-10001 | B2: 21-07-2024 | C2: 27-07-2024 | D2: CUST-4655 | E2: Karan Malhotra | F2: Consumer | G2: North | H2: Rajasthan | I2: Jaipur | J2: Office Supplies | K2: Paper | L2: Pro Paper 122 | M2: Second Class | N2: 8 | O2: 2976.45 | P2: 0.2 | Q2: 19049.28 | R2: 15841.89 | S2: Paid | T2: Completed | U2: 19049.28 | V2: 3207.39 | W2: 7 | X2: 2024
A3: ORD-2024-10002 | B3: 31-08-2024 | C3: 05-09-2024 | D3: CUST-2054 | E3: Mira Das | F3: Small Business | G3: East | H3: Odisha | I3: Bhubaneswar | J3: Furniture | K3: Tables | L3: Pro Tables 258 | M3: Same Day | N3: 3 | O3: 2437.5 | P3: 0 | Q3: 7312.5 | R3: 4904.73 | S3: Paid | T3: Completed | U3: 7312.5 | V3: 2407.77 | W3: 8 | X3: 2024
A4: ORD-2024-10003 | B4: 08-06-2024 | C4: 15-06-2024 | D4: CUST-6843 | E4: Isha Nair | F4: Consumer | G4: East | H4: Odisha | I4: Bhubaneswar | J4: Office Supplies | K4: Art | L4: Elite Art 525 | M4: First Class | N4: 4 | O4: 1065.43 | P4: 0.55 | Q4: 4261.72 | R4: 2465.69 | S4: Paid | T4: Completed | U4: 1917.774 | V4: -547.916 | W4: 6 | X4: 2024
A5: ORD-2024-10004 | B5: 28-11-2024 | C5: 29-11-2024 | D5: CUST-3722 | E5: Arjun Bose | F5: Small Business | G5: South | H5: Telangana | I5: Hyderabad | J5: Furniture | K5: Furnishings | L5: Smart Furnishings 294 | M5: Standard Class | N5: 6 | O5: 1848.43 | P5: 0.25 | Q5: 8317.93 | R5: 6796.77 | S5: Paid | T5: Completed | U5: 8317.935 | V5: 1521.165 | W5: 11 | X5: 2024
A6: ORD-2025-10005 | B6: 29-08-2025 | C6: 01-09-2025 | D6: CUST-8130 | E6: Ananya Rao | F6: Small Business | G6: West | H6: Maharashtra | I6: Mumbai | J6: Furniture | K6: Chairs | L6: Elite Chairs 543 | M6: First Class | N6: 7 | O6: 2973.76 | P6: 0 | Q6: 20816.32 | R6: 17705.37 | S6: Paid | T6: Cancelled | U6: 20816.32 | V6: 3110.95 | W6: 8 | X6: 2025
A7: ORD-2024-10006 | B7: 24-05-2024 | C7: 28-05-2024 | D7: CUST-6056 | E7: Vikram Iyer | F7: Small Business | G7: West | H7: Madhya Pradesh | I7: Indore | J7: Technology | K7: Accessories | L7: Pro Accessories 821 | M7: Same Day | N7: 3 | O7: 1053.11 | P7: 0.2 | Q7: 2527.46 | R7: 1533.58 | S7: Paid | T7: Completed | U7: 2527.464 | V7: 993.884 | W7: 5 | X7: 2024
A8: ORD-2025-10007 | B8: 10-04-2025 | C8: 16-04-2025 | D8: CUST-3656 | E8: Neha Gupta | F8: Consumer | G8: East | H8: Odisha | I8: Bhubaneswar | J8: Technology | K8: Copiers | L8: Eco Copiers 790 | M8: Standard Class | N8: 4 | O8: 1719.87 | P8: 0.15 | Q8: 5847.56 | R8: 4727.25 | S8: Paid | T8: Completed | U8: 5847.558 | V8: 1120.308 | W8: 4 | X8: 2025
A9: ORD-2025-10008 | B9: 23-02-2025 | C9: 26-02-2025 | D9: CUST-4683 | E9: Isha Nair | F9: Small Business | G9: South | H9: Andhra Pradesh | I9: Vijayawada | J9: Office Supplies | K9: Art | L9: Eco Art 848 | M9: First Class | N9: 1 | O9: 2980.71 | P9: 0 | Q9: 2980.71 | R9: 2357.22 | S9: Paid | T9: Completed | U9: 2980.71 | V9: 623.49 | W9: 2 | X9: 2025
A10: ORD-2024-10009 | B10: 05-11-2024 | C10: 10-11-2024 | D10: CUST-2598 | E10: Aditi Sen | F10: Corporate | G10: South | H10: Telangana | I10: Hyderabad | J10: Office Supplies | K10: Labels | L10: Classic Labels 815 | M10: First Class | N10: 8 | O10: 3134.2 | P10: 0 | Q10: 25073.6 | R10: 17347.23 | S10: Paid | T10: Completed | U10: 25073.6 | V10: 7726.37 | W10: 11 | X10: 2024
A11: ORD-2025-10010 | B11: 07-09-2025 | C11: 12-09-2025 | D11: CUST-2483 | E11: Mira Das | F11: Home Office | G11: South | H11: Telangana | I11: Hyderabad | J11: Office Supplies | K11: Paper | L11: Pro Paper 622 | M11: Second Class | N11: 9 | O11: 852.04 | P11: 0.2 | Q11: 6134.69 | R11: 3800.19 | S11: Paid | T11: Completed | U11: 6134.688 | V11: 2334.498 | W11: 9 | X11: 2025
A12: ORD-2025-10011 | B12: 20-05-2025 | C12: 20-05-2025 | D12: CUST-8092 | E12: Ananya Rao | F12: Corporate | G12: East | H12: West Bengal | I12: Kolkata | J12: Office Supplies | K12: Labels | L12: Prime Labels 644 | M12: Second Class | N12: 3 | O12: 3534.83 | P12: 0.05 | Q12: 10074.27 | R12: 6048.27 | S12: Refunded | T12: Returned | U12: 10074.265 | V12: 4025.9955 | W12: 5 | X12: 2025
A13: ORD-2024-10012 | B13: 22-07-2024 | C13: 23-07-2024 | D13: CUST-6528 | E13: Vikram Iyer | F13: Small Business | G13: East | H13: Odisha | I13: Bhubaneswar | J13: Technology | K13: Accessories | L13: Smart Accessories 603 | M13: Same Day | N13: 6 | O13: 2005.95 | P13: 0.2 | Q13: 9628.56 | R13: 8038.59 | S13: Paid | T13: Completed | U13: 9628.56 | V13: 1589.97 | W13: 7 | X13: 2024
... A913: ORD-2025-10336 | B913: 16-06-2025 | C913: 18-06-2025 | D913: CUST-3621 | E913: Rahul Verma | F913: Home Office | G913: West | H913: Madhya Pradesh | I913: Indore | J913: Office Supplies | K913: Paper | L913: Prime Paper 559 | M913: First Class | N913: 3 | O913: 4289.37 | P913: 0.1 | Q913: 11778.71 | R913: 6829.43 | S913: Paid | T913: Returned | U913: 11581.299 | V913: 4751.869 | W913: 6 | X913: 2025

Sheet 1_By_Region
A1: SALES & PROFIT BY REGION
A2: Formulas use SUMIFS on _Data sheet — Completed + Paid orders only
A4: Region | B4: Total Sales (₹) | C4: Total Profit (₹) | D4: Order Count | E4: Profit Margin %
A5: East | B5: =SUMIFS(_Data!U2:U913,_Data!G2:G913,A5,_Data!T2:T913,"Completed",_Data!S2:S913,"Paid") -> 1382664.4 | C5: =SUMIFS(_Data!V2:V913,_Data!G2:G913,A5,_Data!T2:T913,"Completed",_Data!S2:S913,"Paid") -> 415855.03 | D5: =COUNTIFS(_Data!G2:G913,A5,_Data!T2:T913,"Completed",_Data!S2:S913,"Paid") -> 149 | E5: =IFERROR(C5/B5,"") -> 0.30076353
A6: North | B6: =SUMIFS(_Data!U2:U913,_Data!G2:G913,A6,_Data!T2:T913,"Completed",_Data!S2:S913,"Paid") -> 1282973.1 | C6: =SUMIFS(_Data!V2:V913,_Data!G2:G913,A6,_Data!T2:T913,"Completed",_Data!S2:S913,"Paid") -> 379389.68 | D6: =COUNTIFS(_Data!G2:G913,A6,_Data!T2:T913,"Completed",_Data!S2:S913,"Paid") -> 128 | E6: =IFERROR(C6/B6,"") -> 0.29571133
A7: South | B7: =SUMIFS(_Data!U2:U913,_Data!G2:G913,A7,_Data!T2:T913,"Completed",_Data!S2:S913,"Paid") -> 1603605.8 | C7: =SUMIFS(_Data!V2:V913,_Data!G2:G913,A7,_Data!T2:T913,"Completed",_Data!S2:S913,"Paid") -> 430123.77 | D7: =COUNTIFS(_Data!G2:G913,A7,_Data!T2:T913,"Completed",_Data!S2:S913,"Paid") -> 153 | E7: =IFERROR(C7/B7,"") -> 0.26822288
A8: Unknown | B8: =SUMIFS(_Data!U2:U913,_Data!G2:G913,A8,_Data!T2:T913,"Completed",_Data!S2:S913,"Paid") -> 187898.46 | C8: =SUMIFS(_Data!V2:V913,_Data!G2:G913,A8,_Data!T2:T913,"Completed",_Data!S2:S913,"Paid") -> 63943.192 | D8: =COUNTIFS(_Data!G2:G913,A8,_Data!T2:T913,"Completed",_Data!S2:S913,"Paid") -> 19 | E8: =IFERROR(C8/B8,"") -> 0.34030716
A9: West | B9: =SUMIFS(_Data!U2:U913,_Data!G2:G913,A9,_Data!T2:T913,"Completed",_Data!S2:S913,"Paid") -> 1502507.2 | C9: =SUMIFS(_Data!V2:V913,_Data!G2:G913,A9,_Data!T2:T913,"Completed",_Data!S2:S913,"Paid") -> 433402.26 | D9: =COUNTIFS(_Data!G2:G913,A9,_Data!T2:T913,"Completed",_Data!S2:S913,"Paid") -> 153 | E9: =IFERROR(C9/B9,"") -> 0.2884527
A10: GRAND TOTAL | B10: =SUM(B5:B9) -> 5959648.9 | C10: =SUM(C5:C9) -> 1722713.9 | D10: =SUM(D5:D9) -> 602 | E10: =IFERROR(C10/B10,"") -> 0.28906299

Sheet 2_By_Category
A1: SALES & PROFIT BY CATEGORY & SUB-CATEGORY
A2: SUMIFS formulas — Completed + Paid orders only
A4: Category | B4: Sub-Category | C4: Total Sales (₹) | D4: Total Profit (₹) | E4: Order Count
A5: Furniture | B5: Bookcases | C5: =SUMIFS(_Data!U2:U913,_Data!J2:J913,A5,_Data!K2:K913,B5,_Data!T2:T913,"Completed",_Data!S2:S913,"Paid") -> 410143.26 | D5: =SUMIFS(_Data!V2:V913,_Data!J2:J913,A5,_Data!K2:K913,B5,_Data!T2:T913,"Completed",_Data!S2:S913,"Paid") -> 105141.23 | E5: =COUNTIFS(_Data!J2:J913,A5,_Data!K2:K913,B5,_Data!T2:T913,"Completed",_Data!S2:S913,"Paid") -> 43
A6: Furniture | B6: Chairs | C6: =SUMIFS(_Data!U2:U913,_Data!J2:J913,A6,_Data!K2:K913,B6,_Data!T2:T913,"Completed",_Data!S2:S913,"Paid") -> 583968.65 | D6: =SUMIFS(_Data!V2:V913,_Data!J2:J913,A6,_Data!K2:K913,B6,_Data!T2:T913,"Completed",_Data!S2:S913,"Paid") -> 175651.42 | E6: =COUNTIFS(_Data!J2:J913,A6,_Data!K2:K913,B6,_Data!T2:T913,"Completed",_Data!S2:S913,"Paid") -> 56
A7: Furniture | B7: Furnishings | C7: =SUMIFS(_Data!U2:U913,_Data!J2:J913,A7,_Data!K2:K913,B7,_Data!T2:T913,"Completed",_Data!S2:S913,"Paid") -> 503021.35 | D7: =SUMIFS(_Data!V2:V913,_Data!J2:J913,A7,_Data!K2:K913,B7,_Data!T2:T913,"Completed",_Data!S2:S913,"Paid") -> 146832.71 | E7: =COUNTIFS(_Data!J2:J913,A7,_Data!K2:K913,B7,_Data!T2:T913,"Completed",_Data!S2:S913,"Paid") -> 51
A8: Furniture | B8: Tables | C8: =SUMIFS(_Data!U2:U913,_Data!J2:J913,A8,_Data!K2:K913,B8,_Data!T2:T913,"Completed",_Data!S2:S913,"Paid") -> 420185.33 | D8: =SUMIFS(_Data!V2:V913,_Data!J2:J913,A8,_Data!K2:K913,B8,_Data!T2:T913,"Completed",_Data!S2:S913,"Paid") -> 127253.69 | E8: =COUNTIFS(_Data!J2:J913,A8,_Data!K2:K913,B8,_Data!T2:T913,"Completed",_Data!S2:S913,"Paid") -> 49
A9: Office Supplies | B9: Art | C9: =SUMIFS(_Data!U2:U913,_Data!J2:J913,A9,_Data!K2:K913,B9,_Data!T2:T913,"Completed",_Data!S2:S913,"Paid") -> 300592.44 | D9: =SUMIFS(_Data!V2:V913,_Data!J2:J913,A9,_Data!K2:K913,B9,_Data!T2:T913,"Completed",_Data!S2:S913,"Paid") -> 80200.777 | E9: =COUNTIFS(_Data!J2:J913,A9,_Data!K2:K913,B9,_Data!T2:T913,"Completed",_Data!S2:S913,"Paid") -> 29
A10: Office Supplies | B10: Binders | C10: =SUMIFS(_Data!U2:U913,_Data!J2:J913,A10,_Data!K2:K913,B10,_Data!T2:T913,"Completed",_Data!S2:S913,"Paid") -> 342853.56 | D10: =SUMIFS(_Data!V2:V913,_Data!J2:J913,A10,_Data!K2:K913,B10,_Data!T2:T913,"Completed",_Data!S2:S913,"Paid") -> 109222.19 | E10: =COUNTIFS(_Data!J2:J913,A10,_Data!K2:K913,B10,_Data!T2:T913,"Completed",_Data!S2:S913,"Paid") -> 34
A11: Office Supplies | B11: Labels | C11: =SUMIFS(_Data!U2:U913,_Data!J2:J913,A11,_Data!K2:K913,B11,_Data!T2:T913,"Completed",_Data!S2:S913,"Paid") -> 209170.53 | D11: =SUMIFS(_Data!V2:V913,_Data!J2:J913,A11,_Data!K2:K913,B11,_Data!T2:T913,"Completed",_Data!S2:S913,"Paid") -> 65166.618 | E11: =COUNTIFS(_Data!J2:J913,A11,_Data!K2:K913,B11,_Data!T2:T913,"Completed",_Data!S2:S913,"Paid") -> 30
A12: Office Supplies | B12: Paper | C12: =SUMIFS(_Data!U2:U913,_Data!J2:J913,A12,_Data!K2:K913,B12,_Data!T2:T913,"Completed",_Data!S2:S913,"Paid") -> 447884.39 | D12: =SUMIFS(_Data!V2:V913,_Data!J2:J913,A12,_Data!K2:K913,B12,_Data!T2:T913,"Completed",_Data!S2:S913,"Paid") -> 123501.05 | E12: =COUNTIFS(_Data!J2:J913,A12,_Data!K2:K913,B12,_Data!T2:T913,"Completed",_Data!S2:S913,"Paid") -> 42
A13: Office Supplies | B13: Storage | C13: =SUMIFS(_Data!U2:U913,_Data!J2:J913,A13,_Data!K2:K913,B13,_Data!T2:T913,"Completed",_Data!S2:S913,"Paid") -> 541888.25 | D13: =SUMIFS(_Data!V2:V913,_Data!J2:J913,A13,_Data!K2:K913,B13,_Data!T2:T913,"Completed",_Data!S2:S913,"Paid") -> 134582.92 | E13: =COUNTIFS(_Data!J2:J913,A13,_Data!K2:K913,B13,_Data!T2:T913,"Completed",_Data!S2:S913,"Paid") -> 55
A14: Technology | B14: Accessories | C14: =SUMIFS(_Data!U2:U913,_Data!J2:J913,A14,_Data!K2:K913,B14,_Data!T2:T913,"Completed",_Data!S2:S913,"Paid") -> 520097.44 | D14: =SUMIFS(_Data!V2:V913,_Data!J2:J913,A14,_Data!K2:K913,B14,_Data!T2:T913,"Completed",_Data!S2:S913,"Paid") -> 148006.45 | E14: =COUNTIFS(_Data!J2:J913,A14,_Data!K2:K913,B14,_Data!T2:T913,"Completed",_Data!S2:S913,"Paid") -> 47
A15: Technology | B15: Copiers | C15: =SUMIFS(_Data!U2:U913,_Data!J2:J913,A15,_Data!K2:K913,B15,_Data!T2:T913,"Completed",_Data!S2:S913,"Paid") -> 670173.31 | D15: =SUMIFS(_Data!V2:V913,_Data!J2:J913,A15,_Data!K2:K913,B15,_Data!T2:T913,"Completed",_Data!S2:S913,"Paid") -> 194107.97 | E15: =COUNTIFS(_Data!J2:J913,A15,_Data!K2:K913,B15,_Data!T2:T913,"Completed",_Data!S2:S913,"Paid") -> 66
A16: Technology | B16: Machines | C16: =SUMIFS(_Data!U2:U913,_Data!J2:J913,A16,_Data!K2:K913,B16,_Data!T2:T913,"Completed",_Data!S2:S913,"Paid") -> 429529.93 | D16: =SUMIFS(_Data!V2:V913,_Data!J2:J913,A16,_Data!K2:K913,B16,_Data!T2:T913,"Completed",_Data!S2:S913,"Paid") -> 148398.06 | E16: =COUNTIFS(_Data!J2:J913,A16,_Data!K2:K913,B16,_Data!T2:T913,"Completed",_Data!S2:S913,"Paid") -> 47
A17: Technology | B17: Phones | C17: =SUMIFS(_Data!U2:U913,_Data!J2:J913,A17,_Data!K2:K913,B17,_Data!T2:T913,"Completed",_Data!S2:S913,"Paid") -> 580140.5 | D17: =SUMIFS(_Data!V2:V913,_Data!J2:J913,A17,_Data!K2:K913,B17,_Data!T2:T913,"Completed",_Data!S2:S913,"Paid") -> 164648.83 | E17: =COUNTIFS(_Data!J2:J913,A17,_Data!K2:K913,B17,_Data!T2:T913,"Completed",_Data!S2:S913,"Paid") -> 53
A18: GRAND TOTAL | C18: =SUM(C5:C17) -> 5959648.9 | D18: =SUM(D5:D17) -> 1722713.9 | E18: =SUM(E5:E17) -> 602

Sheet 3_By_Ship_Mode
A1: ORDER COUNT BY SHIP MODE
A2: COUNTIF formulas — all orders
A4: Ship Mode | B4: Total Orders | C4: Completed | D4: Cancelled/Returned | E4: % Completed
A5: First Class | B5: =COUNTIF(_Data!M2:M913,A5) -> 223 | C5: =COUNTIFS(_Data!M2:M913,A5,_Data!T2:T913,"Completed") -> 155 | D5: =COUNTIFS(_Data!M2:M913,A5,_Data!T2:T913,"Cancelled")+COUNTIFS(_Data!M2:M913,A5,_Data!T2:T913,"Returned") -> 68 | E5: =IFERROR(C5/B5,"") -> 0.69506726
A6: Same Day | B6: =COUNTIF(_Data!M2:M913,A6) -> 204 | C6: =COUNTIFS(_Data!M2:M913,A6,_Data!T2:T913,"Completed") -> 132 | D6: =COUNTIFS(_Data!M2:M913,A6,_Data!T2:T913,"Cancelled")+COUNTIFS(_Data!M2:M913,A6,_Data!T2:T913,"Returned") -> 72 | E6: =IFERROR(C6/B6,"") -> 0.64705882
A7: Second Class | B7: =COUNTIF(_Data!M2:M913,A7) -> 222 | C7: =COUNTIFS(_Data!M2:M913,A7,_Data!T2:T913,"Completed") -> 144 | D7: =COUNTIFS(_Data!M2:M913,A7,_Data!T2:T913,"Cancelled")+COUNTIFS(_Data!M2:M913,A7,_Data!T2:T913,"Returned") -> 78 | E7: =IFERROR(C7/B7,"") -> 0.64864865
A8: Standard Class | B8: =COUNTIF(_Data!M2:M913,A8) -> 242 | C8: =COUNTIFS(_Data!M2:M913,A8,_Data!T2:T913,"Completed") -> 158 | D8: =COUNTIFS(_Data!M2:M913,A8,_Data!T2:T913,"Cancelled")+COUNTIFS(_Data!M2:M913,A8,_Data!T2:T913,"Returned") -> 84 | E8: =IFERROR(C8/B8,"") -> 0.65289256
A9: Unknown | B9: =COUNTIF(_Data!M2:M913,A9) -> 21 | C9: =COUNTIFS(_Data!M2:M913,A9,_Data!T2:T913,"Completed") -> 15 | D9: =COUNTIFS(_Data!M2:M913,A9,_Data!T2:T913,"Cancelled")+COUNTIFS(_Data!M2:M913,A9,_Data!T2:T913,"Returned") -> 6 | E9: =IFERROR(C9/B9,"") -> 0.71428571
A10: TOTAL | B10: =SUM(B5:B9) -> 912 | C10: =SUM(C5:C9) -> 604 | D10: =SUM(D5:D9) -> 308

Sheet 4_By_Segment
A1: PROFIT MARGIN BY CUSTOMER SEGMENT
A2: SUMIFS formulas — Completed + Paid orders only
A4: Segment | B4: Total Sales (₹) | C4: Total Profit (₹) | D4: Order Count | E4: Profit Margin %
A5: Consumer | B5: =SUMIFS(_Data!U2:U913,_Data!F2:F913,A5,_Data!T2:T913,"Completed",_Data!S2:S913,"Paid") -> 1444995.2 | C5: =SUMIFS(_Data!V2:V913,_Data!F2:F913,A5,_Data!T2:T913,"Completed",_Data!S2:S913,"Paid") -> 410319.87 | D5: =COUNTIFS(_Data!F2:F913,A5,_Data!T2:T913,"Completed",_Data!S2:S913,"Paid") -> 147 | E5: =IFERROR(C5/B5,"") -> 0.28395934
A6: Corporate | B6: =SUMIFS(_Data!U2:U913,_Data!F2:F913,A6,_Data!T2:T913,"Completed",_Data!S2:S913,"Paid") -> 1312159.6 | C6: =SUMIFS(_Data!V2:V913,_Data!F2:F913,A6,_Data!T2:T913,"Completed",_Data!S2:S913,"Paid") -> 386126.62 | D6: =COUNTIFS(_Data!F2:F913,A6,_Data!T2:T913,"Completed",_Data!S2:S913,"Paid") -> 135 | E6: =IFERROR(C6/B6,"") -> 0.29426802
A7: Home Office | B7: =SUMIFS(_Data!U2:U913,_Data!F2:F913,A7,_Data!T2:T913,"Completed",_Data!S2:S913,"Paid") -> 1558492.6 | C7: =SUMIFS(_Data!V2:V913,_Data!F2:F913,A7,_Data!T2:T913,"Completed",_Data!S2:S913,"Paid") -> 468430.68 | D7: =COUNTIFS(_Data!F2:F913,A7,_Data!T2:T913,"Completed",_Data!S2:S913,"Paid") -> 162 | E7: =IFERROR(C7/B7,"") -> 0.30056651
A8: Small Business | B8: =SUMIFS(_Data!U2:U913,_Data!F2:F913,A8,_Data!T2:T913,"Completed",_Data!S2:S913,"Paid") -> 1644001.6 | C8: =SUMIFS(_Data!V2:V913,_Data!F2:F913,A8,_Data!T2:T913,"Completed",_Data!S2:S913,"Paid") -> 457836.76 | D8: =COUNTIFS(_Data!F2:F913,A8,_Data!T2:T913,"Completed",_Data!S2:S913,"Paid") -> 158 | E8: =IFERROR(C8/B8,"") -> 0.27848924
A9: TOTAL | B9: =SUM(B5:B8) -> 5959648.9 | C9: =SUM(C5:C8) -> 1722713.9 | D9: =SUM(D5:D8) -> 602 | E9: =IFERROR(C9/B9,"") -> 0.28906299

Sheet 5_Cancelled_Refunded_Failed
A1: CANCELLED / RETURNED / FAILED ORDERS BY REGION
A2: COUNTIFS formulas — all orders
A4: Region | B4: Cancelled | C4: Returned | D4: Failed Payment | E4: Refunded | F4: Total Leakage
A5: East | B5: =COUNTIFS(_Data!G2:G913,A5,_Data!T2:T913,"Cancelled") -> 30 | C5: =COUNTIFS(_Data!G2:G913,A5,_Data!T2:T913,"Returned") -> 45 | D5: =COUNTIFS(_Data!G2:G913,A5,_Data!S2:S913,"Failed") -> 13 | E5: =COUNTIFS(_Data!G2:G913,A5,_Data!S2:S913,"Refunded") -> 14 | F5: =SUM(B5:E5) -> 102
A6: North | B6: =COUNTIFS(_Data!G2:G913,A6,_Data!T2:T913,"Cancelled") -> 48 | C6: =COUNTIFS(_Data!G2:G913,A6,_Data!T2:T913,"Returned") -> 37 | D6: =COUNTIFS(_Data!G2:G913,A6,_Data!S2:S913,"Failed") -> 20 | E6: =COUNTIFS(_Data!G2:G913,A6,_Data!S2:S913,"Refunded") -> 20 | F6: =SUM(B6:E6) -> 125
A7: South | B7: =COUNTIFS(_Data!G2:G913,A7,_Data!T2:T913,"Cancelled") -> 35 | C7: =COUNTIFS(_Data!G2:G913,A7,_Data!T2:T913,"Returned") -> 37 | D7: =COUNTIFS(_Data!G2:G913,A7,_Data!S2:S913,"Failed") -> 20 | E7: =COUNTIFS(_Data!G2:G913,A7,_Data!S2:S913,"Refunded") -> 20 | F7: =SUM(B7:E7) -> 112
A8: Unknown | B8: =COUNTIFS(_Data!G2:G913,A8,_Data!T2:T913,"Cancelled") -> 2 | C8: =COUNTIFS(_Data!G2:G913,A8,_Data!T2:T913,"Returned") -> 4 | D8: =COUNTIFS(_Data!G2:G913,A8,_Data!S2:S913,"Failed") -> 2 | E8: =COUNTIFS(_Data!G2:G913,A8,_Data!S2:S913,"Refunded") -> 3 | F8: =SUM(B8:E8) -> 11
A9: West | B9: =COUNTIFS(_Data!G2:G913,A9,_Data!T2:T913,"Cancelled") -> 30 | C9: =COUNTIFS(_Data!G2:G913,A9,_Data!T2:T913,"Returned") -> 40 | D9: =COUNTIFS(_Data!G2:G913,A9,_Data!S2:S913,"Failed") -> 14 | E9: =COUNTIFS(_Data!G2:G913,A9,_Data!S2:S913,"Refunded") -> 14 | F9: =SUM(B9:E9) -> 98
A10: TOTAL | B10: =SUM(B5:B9) -> 145 | C10: =SUM(C5:C9) -> 163 | D10: =SUM(D5:D9) -> 69 | E10: =SUM(E5:E9) -> 71 | F10: =SUM(F5:F9) -> 448

Sheet 6_Monthly_Sales_Trend
A1: MONTHLY SALES TREND
A2: SUMIFS formulas — Completed + Paid orders. W=order_month, X=order_year in _Data
A4: Year | B4: Month | C4: Month Name | D4: Total Sales (₹) | E4: Total Profit (₹) | F4: Order Count
A5: 2024 | B5: 1 | C5: Jan | D5: =SUMIFS(_Data!U2:U913,_Data!X2:X913,A5,_Data!W2:W913,B5,_Data!T2:T913,"Completed",_Data!S2:S913,"Paid") -> 241861.32 | E5: =SUMIFS(_Data!V2:V913,_Data!X2:X913,A5,_Data!W2:W913,B5,_Data!T2:T913,"Completed",_Data!S2:S913,"Paid") -> 77833.842 | F5: =COUNTIFS(_Data!X2:X913,A5,_Data!W2:W913,B5,_Data!T2:T913,"Completed",_Data!S2:S913,"Paid") -> 28
A6: 2024 | B6: 2 | C6: Feb | D6: =SUMIFS(_Data!U2:U913,_Data!X2:X913,A6,_Data!W2:W913,B6,_Data!T2:T913,"Completed",_Data!S2:S913,"Paid") -> 272999.97 | E6: =SUMIFS(_Data!V2:V913,_Data!X2:X913,A6,_Data!W2:W913,B6,_Data!T2:T913,"Completed",_Data!S2:S913,"Paid") -> 85401.395 | F6: =COUNTIFS(_Data!X2:X913,A6,_Data!W2:W913,B6,_Data!T2:T913,"Completed",_Data!S2:S913,"Paid") -> 28
A7: 2024 | B7: 3 | C7: Mar | D7: =SUMIFS(_Data!U2:U913,_Data!X2:X913,A7,_Data!W2:W913,B7,_Data!T2:T913,"Completed",_Data!S2:S913,"Paid") -> 243273.04 | E7: =SUMIFS(_Data!V2:V913,_Data!X2:X913,A7,_Data!W2:W913,B7,_Data!T2:T913,"Completed",_Data!S2:S913,"Paid") -> 71061.977 | F7: =COUNTIFS(_Data!X2:X913,A7,_Data!W2:W913,B7,_Data!T2:T913,"Completed",_Data!S2:S913,"Paid") -> 27
A8: 2024 | B8: 4 | C8: Apr | D8: =SUMIFS(_Data!U2:U913,_Data!X2:X913,A8,_Data!W2:W913,B8,_Data!T2:T913,"Completed",_Data!S2:S913,"Paid") -> 241541.51 | E8: =SUMIFS(_Data!V2:V913,_Data!X2:X913,A8,_Data!W2:W913,B8,_Data!T2:T913,"Completed",_Data!S2:S913,"Paid") -> 67927.845 | F8: =COUNTIFS(_Data!X2:X913,A8,_Data!W2:W913,B8,_Data!T2:T913,"Completed",_Data!S2:S913,"Paid") -> 21
A9: 2024 | B9: 5 | C9: May | D9: =SUMIFS(_Data!U2:U913,_Data!X2:X913,A9,_Data!W2:W913,B9,_Data!T2:T913,"Completed",_Data!S2:S913,"Paid") -> 359038.68 | E9: =SUMIFS(_Data!V2:V913,_Data!X2:X913,A9,_Data!W2:W913,B9,_Data!T2:T913,"Completed",_Data!S2:S913,"Paid") -> 91003.629 | F9: =COUNTIFS(_Data!X2:X913,A9,_Data!W2:W913,B9,_Data!T2:T913,"Completed",_Data!S2:S913,"Paid") -> 34
A10: 2024 | B10: 6 | C10: Jun | D10: =SUMIFS(_Data!U2:U913,_Data!X2:X913,A10,_Data!W2:W913,B10,_Data!T2:T913,"Completed",_Data!S2:S913,"Paid") -> 393187.18 | E10: =SUMIFS(_Data!V2:V913,_Data!X2:X913,A10,_Data!W2:W913,B10,_Data!T2:T913,"Completed",_Data!S2:S913,"Paid") -> 114270.82 | F10: =COUNTIFS(_Data!X2:X913,A10,_Data!W2:W913,B10,_Data!T2:T913,"Completed",_Data!S2:S913,"Paid") -> 33
A11: 2024 | B11: 7 | C11: Jul | D11: =SUMIFS(_Data!U2:U913,_Data!X2:X913,A11,_Data!W2:W913,B11,_Data!T2:T913,"Completed",_Data!S2:S913,"Paid") -> 235720.3 | E11: =SUMIFS(_Data!V2:V913,_Data!X2:X913,A11,_Data!W2:W913,B11,_Data!T2:T913,"Completed",_Data!S2:S913,"Paid") -> 62651.654 | F11: =COUNTIFS(_Data!X2:X913,A11,_Data!W2:W913,B11,_Data!T2:T913,"Completed",_Data!S2:S913,"Paid") -> 27
A12: 2024 | B12: 8 | C12: Aug | D12: =SUMIFS(_Data!U2:U913,_Data!X2:X913,A12,_Data!W2:W913,B12,_Data!T2:T913,"Completed",_Data!S2:S913,"Paid") -> 241428.67 | E12: =SUMIFS(_Data!V2:V913,_Data!X2:X913,A12,_Data!W2:W913,B12,_Data!T2:T913,"Completed",_Data!S2:S913,"Paid") -> 74723.395 | F12: =COUNTIFS(_Data!X2:X913,A12,_Data!W2:W913,B12,_Data!T2:T913,"Completed",_Data!S2:S913,"Paid") -> 30
A13: 2024 | B13: 9 | C13: Sep | D13: =SUMIFS(_Data!U2:U913,_Data!X2:X913,A13,_Data!W2:W913,B13,_Data!T2:T913,"Completed",_Data!S2:S913,"Paid") -> 226234.27 | E13: =SUMIFS(_Data!V2:V913,_Data!X2:X913,A13,_Data!W2:W913,B13,_Data!T2:T913,"Completed",_Data!S2:S913,"Paid") -> 57228.045 | F13: =COUNTIFS(_Data!X2:X913,A13,_Data!W2:W913,B13,_Data!T2:T913,"Completed",_Data!S2:S913,"Paid") -> 23
A14: 2024 | B14: 10 | C14: Oct | D14: =SUMIFS(_Data!U2:U913,_Data!X2:X913,A14,_Data!W2:W913,B14,_Data!T2:T913,"Completed",_Data!S2:S913,"Paid") -> 334481.56 | E14: =SUMIFS(_Data!V2:V913,_Data!X2:X913,A14,_Data!W2:W913,B14,_Data!T2:T913,"Completed",_Data!S2:S913,"Paid") -> 83533.35 | F14: =COUNTIFS(_Data!X2:X913,A14,_Data!W2:W913,B14,_Data!T2:T913,"Completed",_Data!S2:S913,"Paid") -> 30
A15: 2024 | B15: 11 | C15: Nov | D15: =SUMIFS(_Data!U2:U913,_Data!X2:X913,A15,_Data!W2:W913,B15,_Data!T2:T913,"Completed",_Data!S2:S913,"Paid") -> 260061.65 | E15: =SUMIFS(_Data!V2:V913,_Data!X2:X913,A15,_Data!W2:W913,B15,_Data!T2:T913,"Completed",_Data!S2:S913,"Paid") -> 91770.353 | F15: =COUNTIFS(_Data!X2:X913,A15,_Data!W2:W913,B15,_Data!T2:T913,"Completed",_Data!S2:S913,"Paid") -> 23
A16: 2024 | B16: 12 | C16: Dec | D16: =SUMIFS(_Data!U2:U913,_Data!X2:X913,A16,_Data!W2:W913,B16,_Data!T2:T913,"Completed",_Data!S2:S913,"Paid") -> 201157.16 | E16: =SUMIFS(_Data!V2:V913,_Data!X2:X913,A16,_Data!W2:W913,B16,_Data!T2:T913,"Completed",_Data!S2:S913,"Paid") -> 56327.187 | F16: =COUNTIFS(_Data!X2:X913,A16,_Data!W2:W913,B16,_Data!T2:T913,"Completed",_Data!S2:S913,"Paid") -> 24
A17: 2025 | B17: 1 | C17: Jan | D17: =SUMIFS(_Data!U2:U913,_Data!X2:X913,A17,_Data!W2:W913,B17,_Data!T2:T913,"Completed",_Data!S2:S913,"Paid") -> 272866.45 | E17: =SUMIFS(_Data!V2:V913,_Data!X2:X913,A17,_Data!W2:W913,B17,_Data!T2:T913,"Completed",_Data!S2:S913,"Paid") -> 76028.785 | F17: =COUNTIFS(_Data!X2:X913,A17,_Data!W2:W913,B17,_Data!T2:T913,"Completed",_Data!S2:S913,"Paid") -> 27
A18: 2025 | B18: 2 | C18: Feb | D18: =SUMIFS(_Data!U2:U913,_Data!X2:X913,A18,_Data!W2:W913,B18,_Data!T2:T913,"Completed",_Data!S2:S913,"Paid") -> 394995.72 | E18: =SUMIFS(_Data!V2:V913,_Data!X2:X913,A18,_Data!W2:W913,B18,_Data!T2:T913,"Completed",_Data!S2:S913,"Paid") -> 117043.43 | F18: =COUNTIFS(_Data!X2:X913,A18,_Data!W2:W913,B18,_Data!T2:T913,"Completed",_Data!S2:S913,"Paid") -> 39
A19: 2025 | B19: 3 | C19: Mar | D19: =SUMIFS(_Data!U2:U913,_Data!X2:X913,A19,_Data!W2:W913,B19,_Data!T2:T913,"Completed",_Data!S2:S913,"Paid") -> 322614.29 | E19: =SUMIFS(_Data!V2:V913,_Data!X2:X913,A19,_Data!W2:W913,B19,_Data!T2:T913,"Completed",_Data!S2:S913,"Paid") -> 92228.466 | F19: =COUNTIFS(_Data!X2:X913,A19,_Data!W2:W913,B19,_Data!T2:T913,"Completed",_Data!S2:S913,"Paid") -> 27
A20: 2025 | B20: 4 | C20: Apr | D20: =SUMIFS(_Data!U2:U913,_Data!X2:X913,A20,_Data!W2:W913,B20,_Data!T2:T913,"Completed",_Data!S2:S913,"Paid") -> 293107.4 | E20: =SUMIFS(_Data!V2:V913,_Data!X2:X913,A20,_Data!W2:W913,B20,_Data!T2:T913,"Completed",_Data!S2:S913,"Paid") -> 80559.25 | F20: =COUNTIFS(_Data!X2:X913,A20,_Data!W2:W913,B20,_Data!T2:T913,"Completed",_Data!S2:S913,"Paid") -> 35
A21: 2025 | B21: 5 | C21: May | D21: =SUMIFS(_Data!U2:U913,_Data!X2:X913,A21,_Data!W2:W913,B21,_Data!T2:T913,"Completed",_Data!S2:S913,"Paid") -> 246177.85 | E21: =SUMIFS(_Data!V2:V913,_Data!X2:X913,A21,_Data!W2:W913,B21,_Data!T2:T913,"Completed",_Data!S2:S913,"Paid") -> 76545.447 | F21: =COUNTIFS(_Data!X2:X913,A21,_Data!W2:W913,B21,_Data!T2:T913,"Completed",_Data!S2:S913,"Paid") -> 24
A22: 2025 | B22: 6 | C22: Jun | D22: =SUMIFS(_Data!U2:U913,_Data!X2:X913,A22,_Data!W2:W913,B22,_Data!T2:T913,"Completed",_Data!S2:S913,"Paid") -> 218678.33 | E22: =SUMIFS(_Data!V2:V913,_Data!X2:X913,A22,_Data!W2:W913,B22,_Data!T2:T913,"Completed",_Data!S2:S913,"Paid") -> 57180.704 | F22: =COUNTIFS(_Data!X2:X913,A22,_Data!W2:W913,B22,_Data!T2:T913,"Completed",_Data!S2:S913,"Paid") -> 27
A23: 2025 | B23: 7 | C23: Jul | D23: =SUMIFS(_Data!U2:U913,_Data!X2:X913,A23,_Data!W2:W913,B23,_Data!T2:T913,"Completed",_Data!S2:S913,"Paid") -> 258764.04 | E23: =SUMIFS(_Data!V2:V913,_Data!X2:X913,A23,_Data!W2:W913,B23,_Data!T2:T913,"Completed",_Data!S2:S913,"Paid") -> 74288.206 | F23: =COUNTIFS(_Data!X2:X913,A23,_Data!W2:W913,B23,_Data!T2:T913,"Completed",_Data!S2:S913,"Paid") -> 23
A24: 2025 | B24: 8 | C24: Aug | D24: =SUMIFS(_Data!U2:U913,_Data!X2:X913,A24,_Data!W2:W913,B24,_Data!T2:T913,"Completed",_Data!S2:S913,"Paid") -> 262335.28 | E24: =SUMIFS(_Data!V2:V913,_Data!X2:X913,A24,_Data!W2:W913,B24,_Data!T2:T913,"Completed",_Data!S2:S913,"Paid") -> 82704.965 | F24: =COUNTIFS(_Data!X2:X913,A24,_Data!W2:W913,B24,_Data!T2:T913,"Completed",_Data!S2:S913,"Paid") -> 33
A25: 2025 | B25: 9 | C25: Sep | D25: =SUMIFS(_Data!U2:U913,_Data!X2:X913,A25,_Data!W2:W913,B25,_Data!T2:T913,"Completed",_Data!S2:S913,"Paid") -> 317689.5 | E25: =SUMIFS(_Data!V2:V913,_Data!X2:X913,A25,_Data!W2:W913,B25,_Data!T2:T913,"Completed",_Data!S2:S913,"Paid") -> 95438.908 | F25: =COUNTIFS(_Data!X2:X913,A25,_Data!W2:W913,B25,_Data!T2:T913,"Completed",_Data!S2:S913,"Paid") -> 29
A26: 2025 | B26: 10 | C26: Oct | D26: =SUMIFS(_Data!U2:U913,_Data!X2:X913,A26,_Data!W2:W913,B26,_Data!T2:T913,"Completed",_Data!S2:S913,"Paid") -> 121434.8 | E26: =SUMIFS(_Data!V2:V913,_Data!X2:X913,A26,_Data!W2:W913,B26,_Data!T2:T913,"Completed",_Data!S2:S913,"Paid") -> 36962.274 | F26: =COUNTIFS(_Data!X2:X913,A26,_Data!W2:W913,B26,_Data!T2:T913,"Completed",_Data!S2:S913,"Paid") -> 10
A27: TOTAL | D27: =SUM(D5:D26) -> 5959648.9 | E27: =SUM(E5:E26) -> 1722713.9 | F27: =SUM(F5:F26) -> 602
